kt_toolkit/__init__.py
kt_toolkit/models/__init__.py
kt_toolkit/models/model.py
kt_toolkit-0.0.1.dist-info/METADATA
kt_toolkit-0.0.1.dist-info/WHEEL
kt_toolkit-0.0.1.dist-info/top_level.txt
kt_toolkit-0.0.1.dist-info/RECORD
