Metadata-Version: 2.1
Name: kt-toolkit
Version: 0.0.1
Summary: kt_toolkit
Home-page: https://github.com/Liu-lqq/kt_toolkit
Author: LiuQQ
Author-email: voidmain@126.com
License: UNKNOWN
Project-URL: Bug Tracker, https://github.com/Liu-lqq/kt_toolkit/issues
Platform: UNKNOWN
Classifier: Programming Language :: Python :: 3
Classifier: License :: OSI Approved :: MIT License
Classifier: Operating System :: OS Independent
Requires-Python: >=3.5
Requires-Dist: requests
Requires-Dist: pandas
Requires-Dist: tqdm
Requires-Dist: beautifulsoup4
